flowwatch/__init__.py
flowwatch/app.py
flowwatch/cli.py
flowwatch/dashboard.py
flowwatch/decorators.py
flowwatch/fastapi_integration.py
flowwatch/py.typed
flowwatch/static/dashboard.html
flowwatch-0.1.2.dist-info/METADATA
flowwatch-0.1.2.dist-info/WHEEL
flowwatch-0.1.2.dist-info/entry_points.txt
flowwatch-0.1.2.dist-info/licenses/LICENSE
flowwatch-0.1.2.dist-info/RECORD
