Metadata-Version: 2.4
Name: flowwatch
Version: 0.1.2
Summary: Ergonomic, decorator-based wrapper around watchfiles with a beautiful Rich/Typer CLI.
Project-URL: Source, https://github.com/MichielMe/flowwatch
Author-email: Michiel Meire <michiel.meire1@gmail.com>
License: MIT
License-File: LICENSE
Keywords: decorators,file-driven workflows,rich,typer,watchfiles
Classifier: License :: OSI Approved :: MIT License
Classifier: Operating System :: OS Independent
Classifier: Programming Language :: Python
Classifier: Programming Language :: Python :: 3
Classifier: Programming Language :: Python :: 3.11
Classifier: Programming Language :: Python :: 3.12
Requires-Python: >=3.11
Requires-Dist: rich>=14.2.0
Requires-Dist: typer>=0.20.0
Requires-Dist: watchfiles>=1.1.1
Provides-Extra: all
Requires-Dist: fastapi[standard]>=0.115.0; extra == 'all'
Provides-Extra: dashboard
Requires-Dist: starlette>=0.40.0; extra == 'dashboard'
Requires-Dist: uvicorn>=0.30.0; extra == 'dashboard'
Provides-Extra: dev
Requires-Dist: httpx>=0.27.0; extra == 'dev'
Requires-Dist: mypy>=1.13.0; extra == 'dev'
Requires-Dist: pytest-cov>=4.0; extra == 'dev'
Requires-Dist: pytest>=8.0; extra == 'dev'
Requires-Dist: ruff>=0.8.0; extra == 'dev'
Provides-Extra: fastapi
Requires-Dist: fastapi[standard]>=0.115.0; extra == 'fastapi'
